odoo10_addon_l10n_it_account_stamp-10.0.1.0.1.99.dev8-py3.8-nspkg.pth
odoo/addons/l10n_it_account_stamp/README.rst
odoo/addons/l10n_it_account_stamp/__init__.py
odoo/addons/l10n_it_account_stamp/__manifest__.py
odoo/addons/l10n_it_account_stamp/data/data.xml
odoo/addons/l10n_it_account_stamp/i18n/it.po
odoo/addons/l10n_it_account_stamp/i18n/l10n_it_account_stamp.pot
odoo/addons/l10n_it_account_stamp/models/__init__.py
odoo/addons/l10n_it_account_stamp/models/company.py
odoo/addons/l10n_it_account_stamp/models/invoice.py
odoo/addons/l10n_it_account_stamp/models/product.py
odoo/addons/l10n_it_account_stamp/readme/CONFIGURE.rst
odoo/addons/l10n_it_account_stamp/readme/CONTRIBUTORS.rst
odoo/addons/l10n_it_account_stamp/readme/DESCRIPTION.rst
odoo/addons/l10n_it_account_stamp/readme/USAGE.rst
odoo/addons/l10n_it_account_stamp/static/description/icon.png
odoo/addons/l10n_it_account_stamp/static/description/index.html
odoo/addons/l10n_it_account_stamp/views/company_view.xml
odoo/addons/l10n_it_account_stamp/views/invoice_view.xml
odoo/addons/l10n_it_account_stamp/views/product_view.xml
odoo10_addon_l10n_it_account_stamp-10.0.1.0.1.99.dev8.dist-info/METADATA
odoo10_addon_l10n_it_account_stamp-10.0.1.0.1.99.dev8.dist-info/WHEEL
odoo10_addon_l10n_it_account_stamp-10.0.1.0.1.99.dev8.dist-info/namespace_packages.txt
odoo10_addon_l10n_it_account_stamp-10.0.1.0.1.99.dev8.dist-info/top_level.txt
odoo10_addon_l10n_it_account_stamp-10.0.1.0.1.99.dev8.dist-info/RECORD
