Metadata-Version: 2.1
Name: odoo10-addon-l10n-it-account-stamp
Version: 10.0.1.0.1.99.dev8
Summary: Tax stamp automatic management
Home-page: https://github.com/OCA/l10n-italy
Author: Ermanno Gnan, Sergio Corato, Enrico Ganzaroli, Odoo Community Association (OCA)
Author-email: support@odoo-community.org
License: LGPL-3
Platform: UNKNOWN
Classifier: Programming Language :: Python
Classifier: Framework :: Odoo
Classifier: Framework :: Odoo :: 10.0
Classifier: License :: OSI Approved :: GNU Lesser General Public License v3 (LGPLv3)
Requires-Python: ~=2.7
Requires-Dist: odoo <10.1dev,>=10.0
